vllm_metal/__init__.py
vllm_metal/_rs.cpython-312-darwin.so
vllm_metal/config.py
vllm_metal/mlx_backend/__init__.py
vllm_metal/mlx_backend/batch_cache.py
vllm_metal/mlx_backend/cache.py
vllm_metal/mlx_backend/ops.py
vllm_metal/model_runner.py
vllm_metal/platform.py
vllm_metal/pytorch_backend/__init__.py
vllm_metal/pytorch_backend/tensor_bridge.py
vllm_metal/pytorch_backend/weight_converter.py
vllm_metal/server.py
vllm_metal/v1/__init__.py
vllm_metal/v1/model_runner.py
vllm_metal/v1/worker.py
vllm_metal/worker.py
vllm_metal-0.1.0.dist-info/METADATA
vllm_metal-0.1.0.dist-info/WHEEL
vllm_metal-0.1.0.dist-info/entry_points.txt
vllm_metal-0.1.0.dist-info/licenses/LICENSE
vllm_metal-0.1.0.dist-info/RECORD
