Metadata-Version: 2.4
Name: vllm-metal
Version: 0.1.0
Classifier: Development Status :: 3 - Alpha
Classifier: Intended Audience :: Developers
Classifier: Intended Audience :: Science/Research
Classifier: License :: OSI Approved :: Apache Software License
Classifier: Operating System :: MacOS :: MacOS X
Classifier: Programming Language :: Python :: 3.12
Classifier: Programming Language :: Python :: 3.13
Classifier: Programming Language :: Rust
Classifier: Topic :: Scientific/Engineering :: Artificial Intelligence
Requires-Dist: mlx>=0.20.0
Requires-Dist: mlx-lm>=0.20.0
Requires-Dist: mlx-vlm>=0.3.0
Requires-Dist: transformers>=4.40.0
Requires-Dist: accelerate>=0.26.0
Requires-Dist: safetensors>=0.4.0
Requires-Dist: numpy>=1.24.0
Requires-Dist: psutil>=5.9.0
Requires-Dist: fastapi>=0.100.0
Requires-Dist: uvicorn>=0.23.0
Requires-Dist: pydantic>=2.0.0
Requires-Dist: vllm-metal[vllm,dev] ; extra == 'all'
Requires-Dist: pytest>=7.0.0 ; extra == 'dev'
Requires-Dist: pytest-asyncio>=0.21.0 ; extra == 'dev'
Requires-Dist: ruff>=0.1.0 ; extra == 'dev'
Requires-Dist: mypy>=1.0.0 ; extra == 'dev'
Requires-Dist: vllm>=0.13.0 ; extra == 'vllm'
Provides-Extra: all
Provides-Extra: dev
Provides-Extra: vllm
License-File: LICENSE
Summary: vLLM hardware plugin for Apple Silicon - unifies MLX and PyTorch under a single lowering path
Keywords: vllm,metal,mlx,apple,silicon,mps,llm,inference,rust
Author: vLLM Community
License: Apache-2.0
Requires-Python: >=3.12, <3.14
Project-URL: Homepage, https://github.com/vllm-project/vllm-metal
Project-URL: Issues, https://github.com/vllm-project/vllm-metal/issues
Project-URL: Repository, https://github.com/vllm-project/vllm-metal
